{
  "accuracy": null,
  "contest_combos": null,
  "contest_effect": null,
  "contest_type": null,
  "damage_class": {
    "name": "status",
    "url": "https://pokeapi.co/api/v2/move-damage-class/1/"
  },
  "effect_chance": null,
  "effect_changes": [],
  "effect_entries": [
    {
      "effect": "Exchanges the original Speed stats of the user and target.",
      "language": {
        "name": "en",
        "url": "https://pokeapi.co/api/v2/language/9/"
      },
      "short_effect": "Exchanges the user's Speed with the target's."
    }
  ],
  "flavor_text_entries": [
    {
      "flavor_text": "将对手和自己的速度\n进行互换。",
      "language": {
        "name": "zh-Hans",
        "url": "https://pokeapi.co/api/v2/language/12/"
      },
      "version_group": {
        "name": "ultra-sun-ultra-moon",
        "url": "https://pokeapi.co/api/v2/version-group/18/"
      }
    },
    {
      "flavor_text": "相手の　素早さと\n自分の　素早さを\n入れ替えてしまう。",
      "language": {
        "name": "ja",
        "url": "https://pokeapi.co/api/v2/language/11/"
      },
      "version_group": {
        "name": "ultra-sun-ultra-moon",
        "url": "https://pokeapi.co/api/v2/version-group/18/"
      }
    },
    {
      "flavor_text": "The user exchanges Speed stats with the target.",
      "language": {
        "name": "en",
        "url": "https://pokeapi.co/api/v2/language/9/"
      },
      "version_group": {
        "name": "ultra-sun-ultra-moon",
        "url": "https://pokeapi.co/api/v2/version-group/18/"
      }
    },
    {
      "flavor_text": "Chi la usa scambia la propria Velocità\ncon quella del bersaglio.",
      "language": {
        "name": "it",
        "url": "https://pokeapi.co/api/v2/language/8/"
      },
      "version_group": {
        "name": "ultra-sun-ultra-moon",
        "url": "https://pokeapi.co/api/v2/version-group/18/"
      }
    },
    {
      "flavor_text": "Intercambia su Velocidad por la del oponente.",
      "language": {
        "name": "es",
        "url": "https://pokeapi.co/api/v2/language/7/"
      },
      "version_group": {
        "name": "ultra-sun-ultra-moon",
        "url": "https://pokeapi.co/api/v2/version-group/18/"
      }
    },
    {
      "flavor_text": "Der Anwender tauscht seinen Initiative-Wert mit dem\ndes Zieles.",
      "language": {
        "name": "de",
        "url": "https://pokeapi.co/api/v2/language/6/"
      },
      "version_group": {
        "name": "ultra-sun-ultra-moon",
        "url": "https://pokeapi.co/api/v2/version-group/18/"
      }
    },
    {
      "flavor_text": "Intervertit la Vitesse du lanceur et celle de la cible.",
      "language": {
        "name": "fr",
        "url": "https://pokeapi.co/api/v2/language/5/"
      },
      "version_group": {
        "name": "ultra-sun-ultra-moon",
        "url": "https://pokeapi.co/api/v2/version-group/18/"
      }
    },
    {
      "flavor_text": "將對手和自己的速度\n進行互換。",
      "language": {
        "name": "zh-Hant",
        "url": "https://pokeapi.co/api/v2/language/4/"
      },
      "version_group": {
        "name": "ultra-sun-ultra-moon",
        "url": "https://pokeapi.co/api/v2/version-group/18/"
      }
    },
    {
      "flavor_text": "상대의 스피드와\n자신의 스피드를\n교체한다.",
      "language": {
        "name": "ko",
        "url": "https://pokeapi.co/api/v2/language/3/"
      },
      "version_group": {
        "name": "ultra-sun-ultra-moon",
        "url": "https://pokeapi.co/api/v2/version-group/18/"
      }
    },
    {
      "flavor_text": "あいての　すばやさと\nじぶんの　すばやさを\nいれかえて　しまう。",
      "language": {
        "name": "ja-Hrkt",
        "url": "https://pokeapi.co/api/v2/language/1/"
      },
      "version_group": {
        "name": "ultra-sun-ultra-moon",
        "url": "https://pokeapi.co/api/v2/version-group/18/"
      }
    },
    {
      "flavor_text": "将对手和自己的速度\n进行互换。",
      "language": {
        "name": "zh-Hans",
        "url": "https://pokeapi.co/api/v2/language/12/"
      },
      "version_group": {
        "name": "sun-moon",
        "url": "https://pokeapi.co/api/v2/version-group/17/"
      }
    },
    {
      "flavor_text": "相手の　素早さと\n自分の　素早さを\n入れ替えてしまう。",
      "language": {
        "name": "ja",
        "url": "https://pokeapi.co/api/v2/language/11/"
      },
      "version_group": {
        "name": "sun-moon",
        "url": "https://pokeapi.co/api/v2/version-group/17/"
      }
    },
    {
      "flavor_text": "The user exchanges Speed stats with the target.",
      "language": {
        "name": "en",
        "url": "https://pokeapi.co/api/v2/language/9/"
      },
      "version_group": {
        "name": "sun-moon",
        "url": "https://pokeapi.co/api/v2/version-group/17/"
      }
    },
    {
      "flavor_text": "Chi la usa scambia la propria Velocità\ncon quella del bersaglio.",
      "language": {
        "name": "it",
        "url": "https://pokeapi.co/api/v2/language/8/"
      },
      "version_group": {
        "name": "sun-moon",
        "url": "https://pokeapi.co/api/v2/version-group/17/"
      }
    },
    {
      "flavor_text": "Intercambia su Velocidad por la del oponente.",
      "language": {
        "name": "es",
        "url": "https://pokeapi.co/api/v2/language/7/"
      },
      "version_group": {
        "name": "sun-moon",
        "url": "https://pokeapi.co/api/v2/version-group/17/"
      }
    },
    {
      "flavor_text": "Der Anwender tauscht seinen Initiative-Wert mit dem\ndes Zieles.",
      "language": {
        "name": "de",
        "url": "https://pokeapi.co/api/v2/language/6/"
      },
      "version_group": {
        "name": "sun-moon",
        "url": "https://pokeapi.co/api/v2/version-group/17/"
      }
    },
    {
      "flavor_text": "Intervertit la Vitesse du lanceur et celle de la cible.",
      "language": {
        "name": "fr",
        "url": "https://pokeapi.co/api/v2/language/5/"
      },
      "version_group": {
        "name": "sun-moon",
        "url": "https://pokeapi.co/api/v2/version-group/17/"
      }
    },
    {
      "flavor_text": "將對手和自己的速度\n進行互換。",
      "language": {
        "name": "zh-Hant",
        "url": "https://pokeapi.co/api/v2/language/4/"
      },
      "version_group": {
        "name": "sun-moon",
        "url": "https://pokeapi.co/api/v2/version-group/17/"
      }
    },
    {
      "flavor_text": "상대의 스피드와\n자신의 스피드를\n교체한다.",
      "language": {
        "name": "ko",
        "url": "https://pokeapi.co/api/v2/language/3/"
      },
      "version_group": {
        "name": "sun-moon",
        "url": "https://pokeapi.co/api/v2/version-group/17/"
      }
    },
    {
      "flavor_text": "あいての　すばやさと\nじぶんの　すばやさを\nいれかえて　しまう。",
      "language": {
        "name": "ja-Hrkt",
        "url": "https://pokeapi.co/api/v2/language/1/"
      },
      "version_group": {
        "name": "sun-moon",
        "url": "https://pokeapi.co/api/v2/version-group/17/"
      }
    }
  ],
  "generation": {
    "name": "generation-vii",
    "url": "https://pokeapi.co/api/v2/generation/7/"
  },
  "id": 683,
  "machines": [],
  "meta": {
    "ailment": {
      "name": "none",
      "url": "https://pokeapi.co/api/v2/move-ailment/0/"
    },
    "ailment_chance": 0,
    "category": {
      "name": "unique",
      "url": "https://pokeapi.co/api/v2/move-category/13/"
    },
    "crit_rate": 0,
    "drain": 0,
    "flinch_chance": 0,
    "healing": 0,
    "max_hits": null,
    "max_turns": null,
    "min_hits": null,
    "min_turns": null,
    "stat_chance": 0
  },
  "name": "speed-swap",
  "names": [
    {
      "language": {
        "name": "zh-Hans",
        "url": "https://pokeapi.co/api/v2/language/12/"
      },
      "name": "速度互换"
    },
    {
      "language": {
        "name": "ja",
        "url": "https://pokeapi.co/api/v2/language/11/"
      },
      "name": "スピードスワップ"
    },
    {
      "language": {
        "name": "en",
        "url": "https://pokeapi.co/api/v2/language/9/"
      },
      "name": "Speed Swap"
    },
    {
      "language": {
        "name": "it",
        "url": "https://pokeapi.co/api/v2/language/8/"
      },
      "name": "Velociscambio"
    },
    {
      "language": {
        "name": "es",
        "url": "https://pokeapi.co/api/v2/language/7/"
      },
      "name": "Cambia Velocidad"
    },
    {
      "language": {
        "name": "de",
        "url": "https://pokeapi.co/api/v2/language/6/"
      },
      "name": "Initiativetausch"
    },
    {
      "language": {
        "name": "fr",
        "url": "https://pokeapi.co/api/v2/language/5/"
      },
      "name": "Permuvitesse"
    },
    {
      "language": {
        "name": "zh-Hant",
        "url": "https://pokeapi.co/api/v2/language/4/"
      },
      "name": "速度互換"
    },
    {
      "language": {
        "name": "ko",
        "url": "https://pokeapi.co/api/v2/language/3/"
      },
      "name": "스피드스웹"
    },
    {
      "language": {
        "name": "ja-Hrkt",
        "url": "https://pokeapi.co/api/v2/language/1/"
      },
      "name": "スピードスワップ"
    }
  ],
  "past_values": [],
  "power": null,
  "pp": 10,
  "priority": 0,
  "stat_changes": [],
  "super_contest_effect": null,
  "target": {
    "name": "selected-pokemon",
    "url": "https://pokeapi.co/api/v2/move-target/10/"
  },
  "type": {
    "name": "psychic",
    "url": "https://pokeapi.co/api/v2/type/14/"
  }
}
