{
  "accuracy": 90,
  "contest_combos": null,
  "contest_effect": null,
  "contest_type": null,
  "damage_class": {
    "name": "special",
    "url": "https://pokeapi.co/api/v2/move-damage-class/3/"
  },
  "effect_chance": null,
  "effect_changes": [],
  "effect_entries": [
    {
      "effect": "Inflicts typeless damage equal to half the target's remaining HP.",
      "language": {
        "name": "en",
        "url": "https://pokeapi.co/api/v2/language/9/"
      },
      "short_effect": "Inflicts damage equal to half the target's HP."
    }
  ],
  "flavor_text_entries": [
    {
      "flavor_text": "向对手释放自然之怒。\n对手的ＨＰ会减半。",
      "language": {
        "name": "zh-Hans",
        "url": "https://pokeapi.co/api/v2/language/12/"
      },
      "version_group": {
        "name": "ultra-sun-ultra-moon",
        "url": "https://pokeapi.co/api/v2/version-group/18/"
      }
    },
    {
      "flavor_text": "自然の　怒りを　相手に　ぶつける。\n相手の　ＨＰは　半分に　なる。",
      "language": {
        "name": "ja",
        "url": "https://pokeapi.co/api/v2/language/11/"
      },
      "version_group": {
        "name": "ultra-sun-ultra-moon",
        "url": "https://pokeapi.co/api/v2/version-group/18/"
      }
    },
    {
      "flavor_text": "The user hits the target with the force of nature.\nIt halves the target’s HP.",
      "language": {
        "name": "en",
        "url": "https://pokeapi.co/api/v2/language/9/"
      },
      "version_group": {
        "name": "ultra-sun-ultra-moon",
        "url": "https://pokeapi.co/api/v2/version-group/18/"
      }
    },
    {
      "flavor_text": "Scatena l’ira della natura sul bersaglio\ne ne dimezza i PS.",
      "language": {
        "name": "it",
        "url": "https://pokeapi.co/api/v2/language/8/"
      },
      "version_group": {
        "name": "ultra-sun-ultra-moon",
        "url": "https://pokeapi.co/api/v2/version-group/18/"
      }
    },
    {
      "flavor_text": "Golpea al objetivo con la furia de la naturaleza y\nreduce sus PS a la mitad.",
      "language": {
        "name": "es",
        "url": "https://pokeapi.co/api/v2/language/7/"
      },
      "version_group": {
        "name": "ultra-sun-ultra-moon",
        "url": "https://pokeapi.co/api/v2/version-group/18/"
      }
    },
    {
      "flavor_text": "Das Ziel wird vom Zorn der Natur getroffen und\nverliert dadurch die Hälfte seiner KP.",
      "language": {
        "name": "de",
        "url": "https://pokeapi.co/api/v2/language/6/"
      },
      "version_group": {
        "name": "ultra-sun-ultra-moon",
        "url": "https://pokeapi.co/api/v2/version-group/18/"
      }
    },
    {
      "flavor_text": "Le lanceur déchaîne toute la colère de la nature\npour baisser les PV de la cible de moitié.",
      "language": {
        "name": "fr",
        "url": "https://pokeapi.co/api/v2/language/5/"
      },
      "version_group": {
        "name": "ultra-sun-ultra-moon",
        "url": "https://pokeapi.co/api/v2/version-group/18/"
      }
    },
    {
      "flavor_text": "向對手發洩自然之怒。\n會使對手的ＨＰ減半。",
      "language": {
        "name": "zh-Hant",
        "url": "https://pokeapi.co/api/v2/language/4/"
      },
      "version_group": {
        "name": "ultra-sun-ultra-moon",
        "url": "https://pokeapi.co/api/v2/version-group/18/"
      }
    },
    {
      "flavor_text": "자연의 분노를 상대에게 부딪친다.\n상대의 HP는 절반이 된다.",
      "language": {
        "name": "ko",
        "url": "https://pokeapi.co/api/v2/language/3/"
      },
      "version_group": {
        "name": "ultra-sun-ultra-moon",
        "url": "https://pokeapi.co/api/v2/version-group/18/"
      }
    },
    {
      "flavor_text": "しぜんの　いかりを　あいてに　ぶつける。\nあいての　ＨＰは　はんぶんに　なる。",
      "language": {
        "name": "ja-Hrkt",
        "url": "https://pokeapi.co/api/v2/language/1/"
      },
      "version_group": {
        "name": "ultra-sun-ultra-moon",
        "url": "https://pokeapi.co/api/v2/version-group/18/"
      }
    },
    {
      "flavor_text": "向对手释放自然之怒。\n对手的ＨＰ会减半。",
      "language": {
        "name": "zh-Hans",
        "url": "https://pokeapi.co/api/v2/language/12/"
      },
      "version_group": {
        "name": "sun-moon",
        "url": "https://pokeapi.co/api/v2/version-group/17/"
      }
    },
    {
      "flavor_text": "自然の　怒りを　相手に　ぶつける。\n相手の　ＨＰは　半分に　なる。",
      "language": {
        "name": "ja",
        "url": "https://pokeapi.co/api/v2/language/11/"
      },
      "version_group": {
        "name": "sun-moon",
        "url": "https://pokeapi.co/api/v2/version-group/17/"
      }
    },
    {
      "flavor_text": "The user hits the target with the force of nature.\nIt halves the target’s HP.",
      "language": {
        "name": "en",
        "url": "https://pokeapi.co/api/v2/language/9/"
      },
      "version_group": {
        "name": "sun-moon",
        "url": "https://pokeapi.co/api/v2/version-group/17/"
      }
    },
    {
      "flavor_text": "Scatena l’ira della natura sul bersaglio\ne ne dimezza i PS.",
      "language": {
        "name": "it",
        "url": "https://pokeapi.co/api/v2/language/8/"
      },
      "version_group": {
        "name": "sun-moon",
        "url": "https://pokeapi.co/api/v2/version-group/17/"
      }
    },
    {
      "flavor_text": "Golpea al objetivo con la furia de la naturaleza y\nreduce sus PS a la mitad.",
      "language": {
        "name": "es",
        "url": "https://pokeapi.co/api/v2/language/7/"
      },
      "version_group": {
        "name": "sun-moon",
        "url": "https://pokeapi.co/api/v2/version-group/17/"
      }
    },
    {
      "flavor_text": "Das Ziel wird vom Zorn der Natur getroffen und\nverliert dadurch die Hälfte seiner KP.",
      "language": {
        "name": "de",
        "url": "https://pokeapi.co/api/v2/language/6/"
      },
      "version_group": {
        "name": "sun-moon",
        "url": "https://pokeapi.co/api/v2/version-group/17/"
      }
    },
    {
      "flavor_text": "Le lanceur déchaîne toute la colère de la nature\npour baisser les PV de la cible de moitié.",
      "language": {
        "name": "fr",
        "url": "https://pokeapi.co/api/v2/language/5/"
      },
      "version_group": {
        "name": "sun-moon",
        "url": "https://pokeapi.co/api/v2/version-group/17/"
      }
    },
    {
      "flavor_text": "向對手發洩自然之怒。\n會使對手的ＨＰ減半。",
      "language": {
        "name": "zh-Hant",
        "url": "https://pokeapi.co/api/v2/language/4/"
      },
      "version_group": {
        "name": "sun-moon",
        "url": "https://pokeapi.co/api/v2/version-group/17/"
      }
    },
    {
      "flavor_text": "자연의 분노를 상대에게 부딪친다.\n상대의 HP는 절반이 된다.",
      "language": {
        "name": "ko",
        "url": "https://pokeapi.co/api/v2/language/3/"
      },
      "version_group": {
        "name": "sun-moon",
        "url": "https://pokeapi.co/api/v2/version-group/17/"
      }
    },
    {
      "flavor_text": "しぜんの　いかりを　あいてに　ぶつける。\nあいての　ＨＰは　はんぶんに　なる。",
      "language": {
        "name": "ja-Hrkt",
        "url": "https://pokeapi.co/api/v2/language/1/"
      },
      "version_group": {
        "name": "sun-moon",
        "url": "https://pokeapi.co/api/v2/version-group/17/"
      }
    }
  ],
  "generation": {
    "name": "generation-vii",
    "url": "https://pokeapi.co/api/v2/generation/7/"
  },
  "id": 717,
  "machines": [],
  "meta": {
    "ailment": {
      "name": "none",
      "url": "https://pokeapi.co/api/v2/move-ailment/0/"
    },
    "ailment_chance": 0,
    "category": {
      "name": "damage",
      "url": "https://pokeapi.co/api/v2/move-category/0/"
    },
    "crit_rate": 0,
    "drain": 0,
    "flinch_chance": 0,
    "healing": 0,
    "max_hits": null,
    "max_turns": null,
    "min_hits": null,
    "min_turns": null,
    "stat_chance": 0
  },
  "name": "natures-madness",
  "names": [
    {
      "language": {
        "name": "zh-Hans",
        "url": "https://pokeapi.co/api/v2/language/12/"
      },
      "name": "自然之怒"
    },
    {
      "language": {
        "name": "ja",
        "url": "https://pokeapi.co/api/v2/language/11/"
      },
      "name": "しぜんのいかり"
    },
    {
      "language": {
        "name": "en",
        "url": "https://pokeapi.co/api/v2/language/9/"
      },
      "name": "Nature’s Madness"
    },
    {
      "language": {
        "name": "it",
        "url": "https://pokeapi.co/api/v2/language/8/"
      },
      "name": "Ira della Natura"
    },
    {
      "language": {
        "name": "es",
        "url": "https://pokeapi.co/api/v2/language/7/"
      },
      "name": "Furia Natural"
    },
    {
      "language": {
        "name": "de",
        "url": "https://pokeapi.co/api/v2/language/6/"
      },
      "name": "Naturzorn"
    },
    {
      "language": {
        "name": "fr",
        "url": "https://pokeapi.co/api/v2/language/5/"
      },
      "name": "Ire de la Nature"
    },
    {
      "language": {
        "name": "zh-Hant",
        "url": "https://pokeapi.co/api/v2/language/4/"
      },
      "name": "自然之怒"
    },
    {
      "language": {
        "name": "ko",
        "url": "https://pokeapi.co/api/v2/language/3/"
      },
      "name": "자연의분노"
    },
    {
      "language": {
        "name": "ja-Hrkt",
        "url": "https://pokeapi.co/api/v2/language/1/"
      },
      "name": "しぜんのいかり"
    }
  ],
  "past_values": [],
  "power": null,
  "pp": 10,
  "priority": 0,
  "stat_changes": [],
  "super_contest_effect": null,
  "target": {
    "name": "selected-pokemon",
    "url": "https://pokeapi.co/api/v2/move-target/10/"
  },
  "type": {
    "name": "fairy",
    "url": "https://pokeapi.co/api/v2/type/18/"
  }
}
